cfbd/__init__.py
cfbd/api_client.py
cfbd/api_response.py
cfbd/configuration.py
cfbd/exceptions.py
cfbd/py.typed
cfbd/rest.py
cfbd/api/__init__.py
cfbd/api/adjusted_metrics_api.py
cfbd/api/betting_api.py
cfbd/api/coaches_api.py
cfbd/api/conferences_api.py
cfbd/api/draft_api.py
cfbd/api/drives_api.py
cfbd/api/games_api.py
cfbd/api/info_api.py
cfbd/api/metrics_api.py
cfbd/api/players_api.py
cfbd/api/plays_api.py
cfbd/api/rankings_api.py
cfbd/api/ratings_api.py
cfbd/api/recruiting_api.py
cfbd/api/stats_api.py
cfbd/api/teams_api.py
cfbd/api/venues_api.py
cfbd/models/__init__.py
cfbd/models/adjusted_metrics.py
cfbd/models/adjusted_metrics_epa.py
cfbd/models/adjusted_metrics_rushing.py
cfbd/models/adjusted_metrics_success_rate.py
cfbd/models/adjusted_team_metrics.py
cfbd/models/adjusted_team_metrics_epa.py
cfbd/models/adjusted_team_metrics_rushing.py
cfbd/models/adjusted_team_metrics_success_rate.py
cfbd/models/advanced_box_score.py
cfbd/models/advanced_box_score_game_info.py
cfbd/models/advanced_box_score_players.py
cfbd/models/advanced_box_score_teams.py
cfbd/models/advanced_game_stat.py
cfbd/models/advanced_game_stat_defense.py
cfbd/models/advanced_game_stat_offense.py
cfbd/models/advanced_game_stat_offense_passing_downs.py
cfbd/models/advanced_game_stat_offense_passing_plays.py
cfbd/models/advanced_season_stat.py
cfbd/models/advanced_season_stat_defense.py
cfbd/models/advanced_season_stat_offense.py
cfbd/models/advanced_season_stat_offense_field_position.py
cfbd/models/advanced_season_stat_offense_havoc.py
cfbd/models/advanced_season_stat_offense_passing_downs.py
cfbd/models/advanced_season_stat_offense_passing_plays.py
cfbd/models/aggregated_team_recruiting.py
cfbd/models/betting_game.py
cfbd/models/calendar_week.py
cfbd/models/coach.py
cfbd/models/coach_season.py
cfbd/models/conference.py
cfbd/models/conference_sp.py
cfbd/models/conference_sp_defense.py
cfbd/models/conference_sp_offense.py
cfbd/models/division_classification.py
cfbd/models/draft_pick.py
cfbd-5.13.1.dist-info/METADATA
cfbd-5.13.1.dist-info/WHEEL
cfbd-5.13.1.dist-info/top_level.txt
cfbd-5.13.1.dist-info/RECORD
