Metadata-Version: 2.4
Name: cfbd
Version: 5.13.1
Summary: College Football Data API
Home-page: https://github.com/CFBD/cfbd-python
Author-email: admin@collegefootballdata.com
License: MIT
Keywords: OpenAPI,OpenAPI-Generator,College Football Data API
Requires-Dist: urllib3<3.0.0,>=1.25.3
Requires-Dist: python-dateutil
Requires-Dist: pydantic<2,>=1.10.5
Requires-Dist: aenum
Dynamic: author-email
Dynamic: description
Dynamic: description-content-type
Dynamic: home-page
Dynamic: keywords
Dynamic: license
Dynamic: requires-dist
Dynamic: summary
